tools_executor/__init__.py
tools_executor/cli.py
tools_executor-0.1.0.dist-info/WHEEL
tools_executor-0.1.0.dist-info/entry_points.txt
tools_executor-0.1.0.dist-info/METADATA
tools_executor-0.1.0.dist-info/RECORD
