Metadata-Version: 2.3
Name: tools-executor
Version: 0.1.0
Summary: Run a FastMCP proxy that lists and invokes every MCP tool from the CLI or an HTTP server.
Keywords: mcp,fastmcp,automation,cli,tools
Author: LiuVaayne
License: MIT License
Classifier: Development Status :: 3 - Alpha
Classifier: Intended Audience :: Developers
Classifier: License :: OSI Approved :: MIT License
Classifier: Programming Language :: Python :: 3
Classifier: Programming Language :: Python :: 3.12
Classifier: Topic :: Software Development :: Libraries :: Application Frameworks
Requires-Dist: click>=8.3.0
Requires-Dist: fastmcp>=2.13.0.2
Requires-Dist: jinja2>=3.1.6
Requires-Python: >=3.12
